<?xml version="1.0" encoding="utf-8"?>
<HIVacSim xmlns:xsi="http://www.w3.org/2001/XMLSchema-instance" 
          xmlns="urn:HIVacSim" xsi:schemaLocation="urn:HIVacSim HIVacSimData.xsd" 
          Title="Simulation Models for the Control of the Dynamics of HIV Infection Through Vaccination" 
          by="Israel Vieira" 
          Version="1.1">
  <!--Scenario's simulation settings definition.-->
  <Scenario>
    <Description>Brazilian Population Sexual Behaviour and Perceptions of HIV/AIDS Survey, July 1999</Description>
    <SimClock>Month</SimClock>
    <RunDuration>144</RunDuration>
    <NumberOfRuns>10</NumberOfRuns>
    <WarmUpType>Traditional</WarmUpType>
    <WarmUp>24</WarmUp>
    <WarmUpMaxConcurrent>2</WarmUpMaxConcurrent>
    <WarmUpPrConcurrent>0.5</WarmUpPrConcurrent>
    <WarmUpInfected>
      <Distribution>Average</Distribution>
      <ParamOne>1</ParamOne>
      <ParamTwo>0</ParamTwo>
      <ParamThree>0</ParamThree>
      <ParamFour>0</ParamFour>
    </WarmUpInfected>
    <Speed>100</Speed>
    <MaxDelay>2000</MaxDelay>
    <Animation>false</Animation>
    <AutoSeed>true</AutoSeed>
    <CustomSeed>19650218</CustomSeed>
    <PLNumerical>500</PLNumerical>
    <PLEstimate>400</PLEstimate>
    <PLAlgorithm>0.13</PLAlgorithm>
  </Scenario>
  <!--Define the disease of interest to be simulated-->
  <Disease>
    <Name>HIV/AIDS</Name>
    <Male2Female>0.003</Male2Female>
    <Female2Male>0.002</Female2Male>
    <Male2Male>0.01</Male2Male>
    <LifeInfection>true</LifeInfection>
    <STDDuration>
      <Distribution>Average</Distribution>
      <ParamOne>0</ParamOne>
      <ParamTwo>0</ParamTwo>
      <ParamThree>0</ParamThree>
      <ParamFour>0</ParamFour>
    </STDDuration>
    <AllowReinfection>false</AllowReinfection>
    <Mortality>0.98</Mortality>
    <LifeExpectancy>
      <Distribution>Uniform</Distribution>
      <ParamOne>84</ParamOne>
      <ParamTwo>144</ParamTwo>
      <ParamThree>0</ParamThree>
      <ParamFour>0</ParamFour>
    </LifeExpectancy>
  </Disease>
  <!--Population Core Groups Definition-->
  <Population Count="3">
    <Group Name="Married">
      <Id>1</Id>
      <Topology>Sphere</Topology>
      <Alpha>0.223853907068936</Alpha>
      <Beta>1</Beta>
      <Radius>6378</Radius>
      <Distance>2406.18087387991</Distance>
      <Degrees>3</Degrees>
      <Size>1422</Size>
      <Age>
        <Distribution>Weibull</Distribution>
        <ParamOne>182.3</ParamOne>
        <ParamTwo>336.28</ParamTwo>
        <ParamThree>2.29</ParamThree>
        <ParamFour>0</ParamFour>
      </Age>
      <LifeExpectancy>
        <Distribution>Average</Distribution>
        <ParamOne>840</ParamOne>
        <ParamTwo>0</ParamTwo>
        <ParamThree>0</ParamThree>
        <ParamFour>0</ParamFour>
      </LifeExpectancy>
      <STDPrevalence>0.007</STDPrevalence>
      <STDAge>
        <Distribution>Weibull</Distribution>
        <ParamOne>0</ParamOne>
        <ParamTwo>64.26</ParamTwo>
        <ParamThree>1.63</ParamThree>
        <ParamFour>0</ParamFour>
      </STDAge>
      <STDTest>0.16</STDTest>
      <Female>0.5</Female>
      <Male>0.5</Male>
      <Homosexual>0.05</Homosexual>
      <MaxConcurrent>5</MaxConcurrent>
      <PrConcurrent>0.06</PrConcurrent>
      <PrNewPartner>1</PrNewPartner>
      <PrCasual>0.06</PrCasual>
      <PrInternal>0.4</PrInternal>
      <StbDuration>
        <Distribution>Weibull</Distribution>
        <ParamOne>0</ParamOne>
        <ParamTwo>198.19</ParamTwo>
        <ParamThree>1.55</ParamThree>
        <ParamFour>0</ParamFour>
      </StbDuration>
      <StbTransitory>
        <Distribution>Gamma</Distribution>
        <ParamOne>0</ParamOne>
        <ParamTwo>20.16</ParamTwo>
        <ParamThree>1.07</ParamThree>
        <ParamFour>0</ParamFour>
      </StbTransitory>
      <StbContacts>
        <Distribution>Gamma</Distribution>
        <ParamOne>0</ParamOne>
        <ParamTwo>4.71</ParamTwo>
        <ParamThree>1.51</ParamThree>
        <ParamFour>0</ParamFour>
      </StbContacts>
      <StbSafeSex>0.11</StbSafeSex>
      <CslDuration>
        <Distribution>Gamma</Distribution>
        <ParamOne>0</ParamOne>
        <ParamTwo>8.84</ParamTwo>
        <ParamThree>1.14</ParamThree>
        <ParamFour>0</ParamFour>
      </CslDuration>
      <CslContacts>
        <Distribution>Gamma</Distribution>
        <ParamOne>0</ParamOne>
        <ParamTwo>5.01</ParamTwo>
        <ParamThree>1.58</ParamThree>
        <ParamFour>0</ParamFour>
      </CslContacts>
      <CslSafeSex>0.12</CslSafeSex>
    </Group>
    <Group Name="Under 25">
      <Id>2</Id>
      <Topology>Sphere</Topology>
      <Alpha>0.222180433131723</Alpha>
      <Beta>1</Beta>
      <Radius>6378</Radius>
      <Distance>3235.61175337638</Distance>
      <Degrees>3</Degrees>
      <Size>794</Size>
      <Age>
        <Distribution>LogNormal</Distribution>
        <ParamOne>143.95</ParamOne>
        <ParamTwo>95.05</ParamTwo>
        <ParamThree>36.99</ParamThree>
        <ParamFour>0</ParamFour>
      </Age>
      <LifeExpectancy>
        <Distribution>Average</Distribution>
        <ParamOne>840</ParamOne>
        <ParamTwo>0</ParamTwo>
        <ParamThree>0</ParamThree>
        <ParamFour>0</ParamFour>
      </LifeExpectancy>
      <STDPrevalence>0.007</STDPrevalence>
      <STDAge>
        <Distribution>Weibull</Distribution>
        <ParamOne>0</ParamOne>
        <ParamTwo>71.79</ParamTwo>
        <ParamThree>1.61</ParamThree>
        <ParamFour>0</ParamFour>
      </STDAge>
      <STDTest>0.12</STDTest>
      <Female>0.45999999999999996</Female>
      <Male>0.54</Male>
      <Homosexual>0.05</Homosexual>
      <MaxConcurrent>5</MaxConcurrent>
      <PrConcurrent>0.21</PrConcurrent>
      <PrNewPartner>0.78</PrNewPartner>
      <PrCasual>0.4</PrCasual>
      <PrInternal>0.8</PrInternal>
      <StbDuration>
        <Distribution>LogNormal</Distribution>
        <ParamOne>0</ParamOne>
        <ParamTwo>29.77</ParamTwo>
        <ParamThree>37.2</ParamThree>
        <ParamFour>0</ParamFour>
      </StbDuration>
      <StbTransitory>
        <Distribution>Weibull</Distribution>
        <ParamOne>0</ParamOne>
        <ParamTwo>14.89</ParamTwo>
        <ParamThree>1.1</ParamThree>
        <ParamFour>0</ParamFour>
      </StbTransitory>
      <StbContacts>
        <Distribution>Gamma</Distribution>
        <ParamOne>0</ParamOne>
        <ParamTwo>6.5</ParamTwo>
        <ParamThree>1.06</ParamThree>
        <ParamFour>0</ParamFour>
      </StbContacts>
      <StbSafeSex>0.47</StbSafeSex>
      <CslDuration>
        <Distribution>Gamma</Distribution>
        <ParamOne>0</ParamOne>
        <ParamTwo>5.25</ParamTwo>
        <ParamThree>1.03</ParamThree>
        <ParamFour>0</ParamFour>
      </CslDuration>
      <CslContacts>
        <Distribution>Gamma</Distribution>
        <ParamOne>0</ParamOne>
        <ParamTwo>7.1</ParamTwo>
        <ParamThree>1.1</ParamThree>
        <ParamFour>0</ParamFour>
      </CslContacts>
      <CslSafeSex>0.55</CslSafeSex>
    </Group>
    <Group Name="Others">
      <Id>3</Id>
      <Topology>Sphere</Topology>
      <Alpha>0.223154451218999</Alpha>
      <Beta>1</Beta>
      <Radius>6378</Radius>
      <Distance>2730.55807954011</Distance>
      <Degrees>3</Degrees>
      <Size>1108</Size>
      <Age>
        <Distribution>InvNormal</Distribution>
        <ParamOne>242.15</ParamOne>
        <ParamTwo>246.94</ParamTwo>
        <ParamThree>612.89</ParamThree>
        <ParamFour>0</ParamFour>
      </Age>
      <LifeExpectancy>
        <Distribution>Average</Distribution>
        <ParamOne>840</ParamOne>
        <ParamTwo>0</ParamTwo>
        <ParamThree>0</ParamThree>
        <ParamFour>0</ParamFour>
      </LifeExpectancy>
      <STDPrevalence>0.007</STDPrevalence>
      <STDAge>
        <Distribution>Weibull</Distribution>
        <ParamOne>0</ParamOne>
        <ParamTwo>64.26</ParamTwo>
        <ParamThree>1.63</ParamThree>
        <ParamFour>0</ParamFour>
      </STDAge>
      <STDTest>0.18</STDTest>
      <Female>0.62</Female>
      <Male>0.38</Male>
      <Homosexual>0.05</Homosexual>
      <MaxConcurrent>5</MaxConcurrent>
      <PrConcurrent>0.14</PrConcurrent>
      <PrNewPartner>0.64</PrNewPartner>
      <PrCasual>0.27</PrCasual>
      <PrInternal>0.7</PrInternal>
      <StbDuration>
        <Distribution>Weibull</Distribution>
        <ParamOne>0</ParamOne>
        <ParamTwo>89.74</ParamTwo>
        <ParamThree>1.01</ParamThree>
        <ParamFour>0</ParamFour>
      </StbDuration>
      <StbTransitory>
        <Distribution>Gamma</Distribution>
        <ParamOne>0</ParamOne>
        <ParamTwo>24.38</ParamTwo>
        <ParamThree>1.03</ParamThree>
        <ParamFour>0</ParamFour>
      </StbTransitory>
      <StbContacts>
        <Distribution>Gamma</Distribution>
        <ParamOne>0</ParamOne>
        <ParamTwo>5.09</ParamTwo>
        <ParamThree>1.34</ParamThree>
        <ParamFour>0</ParamFour>
      </StbContacts>
      <StbSafeSex>0.21</StbSafeSex>
      <CslDuration>
        <Distribution>LogNormal</Distribution>
        <ParamOne>0</ParamOne>
        <ParamTwo>9.16</ParamTwo>
        <ParamThree>14.61</ParamThree>
        <ParamFour>0</ParamFour>
      </CslDuration>
      <CslContacts>
        <Distribution>Gamma</Distribution>
        <ParamOne>0</ParamOne>
        <ParamTwo>5.31</ParamTwo>
        <ParamThree>1.39</ParamThree>
        <ParamFour>0</ParamFour>
      </CslContacts>
      <CslSafeSex>0.42</CslSafeSex>
    </Group>
  </Population>
  <!--Population interaction, digraph adjacency matrix-->
  <AdjMatrix Rows="3" Columns="3">
    <Cell Row="0" Column="0" Data="0" />
    <Cell Row="0" Column="1" Data="0.5" />
    <Cell Row="0" Column="2" Data="0.5" />
    <Cell Row="1" Column="0" Data="0.5" />
    <Cell Row="1" Column="1" Data="0" />
    <Cell Row="1" Column="2" Data="0.5" />
    <Cell Row="2" Column="0" Data="0.5" />
    <Cell Row="2" Column="1" Data="0.5" />
    <Cell Row="2" Column="2" Data="0" />
  </AdjMatrix>
  <!--Preventive vaccine interventions-->
  <Vaccines Count="1">
    <Vaccine Name="ALVAC">
      <Id>1</Id>
      <Effectiveness>0.5</Effectiveness>
      <Lifetime>false</Lifetime>
      <Length>48</Length>
      <UsedBy>1</UsedBy>
    </Vaccine>
  </Vaccines>
  <!--Intervention strategies-->
  <Interventions Count="1">
    <Strategy Name="Everyone safe">
      <Id>1</Id>
      <Active>false</Active>
      <Strategy>AllGroups</Strategy>
      <Groups />
      <Clock>1</Clock>
      <Population>0.6</Population>
      <Vaccine>1</Vaccine>
      <HIVTested>false</HIVTested>
      <HIVResult>NotImportant</HIVResult>
    </Strategy>
  </Interventions>
</HIVacSim>